README.md
setup.py
cnlogs/__init__.py
cnlogs/cnlogs.py
cnlogs.egg-info/PKG-INFO
cnlogs.egg-info/SOURCES.txt
cnlogs.egg-info/dependency_links.txt
cnlogs.egg-info/top_level.txt